k_parse_tool/__init__.py
k_parse_tool/items.py
k_parse_tool/Enum/__init__.py
k_parse_tool/Enum/fix_const_enum.py
k_parse_tool/Enum/item_enum.py
k_parse_tool/Enum/regex_flags.py
k_parse_tool/htmlTemplete/HtmlTableHead.py
k_parse_tool/htmlTemplete/TableTemplete.py
k_parse_tool/htmlTemplete/__init__.py
k_parse_tool/lib/__init__.py
k_parse_tool/lib/column_common_reg.py
k_parse_tool/lib/common_extract_data.py
k_parse_tool/lib/excel_file_process.py
k_parse_tool/lib/file_process_abstract_factory.py
k_parse_tool/lib/file_process_factory.py
k_parse_tool/lib/htmlprocess.py
k_parse_tool/lib/pdf_file_process.py
k_parse_tool/lib/word_file_process.py
k_parse_tool/test/__init__.py
k_parse_tool/test/test_htmlprocess.py
k_parse_tool/test/test_wordprocess.py
k_parse_tool-0.0.10.dist-info/METADATA
k_parse_tool-0.0.10.dist-info/WHEEL
k_parse_tool-0.0.10.dist-info/top_level.txt
k_parse_tool-0.0.10.dist-info/RECORD
