Metadata-Version: 2.1
Name: k-parse-tool
Version: 0.0.10
Summary: parse and extract data from HTML
Home-page: http://xjliu123@192.168.1.200/v3_personal/k-parse-tools.git
Author: kuser
Author-email: xjliu@kland.com.cn
License: GPLv3
Platform: UNKNOWN
Classifier: Programming Language :: Python :: 3
Classifier: License :: OSI Approved :: GNU General Public License v3 (GPLv3)
Classifier: Operating System :: OS Independent
Requires-Python: >=3.6.3
Requires-Dist: pdfplumber (>=0.5.24)
Requires-Dist: python-docx (>=0.8.10)
Requires-Dist: regex (>=2020.11.13)
Requires-Dist: pandas (>=1.1.5)
Requires-Dist: beautifulsoup4 (>=4.9.3)
Requires-Dist: numpy (>=1.18.0)
Requires-Dist: PyDocX (>=0.9.10)
